tjpcov/__init__.py
tjpcov/clusters_helpers.py
tjpcov/covariance_builder.py
tjpcov/covariance_calculator.py
tjpcov/covariance_cluster_counts.py
tjpcov/covariance_cluster_counts_gaussian.py
tjpcov/covariance_cluster_counts_ssc.py
tjpcov/covariance_cluster_mass.py
tjpcov/covariance_fourier_cNG.py
tjpcov/covariance_fourier_cNG_fsky.py
tjpcov/covariance_fourier_gaussian_nmt.py
tjpcov/covariance_fourier_ssc.py
tjpcov/covariance_fourier_ssc_fsky.py
tjpcov/covariance_gaussian_fsky.py
tjpcov/covariance_io.py
tjpcov/tools.py
tjpcov/wigner_transform.py
tjpcov-0.5.1.dist-info/LICENSE
tjpcov-0.5.1.dist-info/METADATA
tjpcov-0.5.1.dist-info/WHEEL
tjpcov-0.5.1.dist-info/top_level.txt
tjpcov-0.5.1.dist-info/RECORD
