Metadata-Version: 2.2
Name: tjpcov
Version: 0.5.1
Summary: Covariances for LSST DESC
Author: LSST DESC
Project-URL: Homepage, https://github.com/LSSTDESC/TJPCov
Project-URL: Bug Tracker, https://github.com/LSSTDESC/TJPCov/issues
Project-URL: Documentation, https://tjpcov.readthedocs.io
Classifier: Development Status :: 4 - Beta
Classifier: Programming Language :: Python :: 3
Classifier: Intended Audience :: Science/Research
Classifier: License :: OSI Approved :: MIT License
Classifier: Operating System :: OS Independent
Classifier: Topic :: Scientific/Engineering :: Physics
Requires-Python: >=3.10
License-File: LICENSE
Requires-Dist: scipy
Requires-Dist: numpy
Requires-Dist: Jinja2
Requires-Dist: pyyaml
Requires-Dist: pyccl>=3.2.0
Requires-Dist: sacc>=0.12
Requires-Dist: camb
Requires-Dist: healpy
Requires-Dist: h5py
Provides-Extra: doc
Requires-Dist: sphinx; extra == "doc"
Requires-Dist: sphinx-autoapi; extra == "doc"
Requires-Dist: sphinx_rtd_theme; extra == "doc"
Requires-Dist: sphinx-book-theme; extra == "doc"
Provides-Extra: nmt
Requires-Dist: pymaster>=2; extra == "nmt"
Provides-Extra: mpi
Requires-Dist: mpi4py; extra == "mpi"
Provides-Extra: full
Requires-Dist: pymaster>=2; extra == "full"
Requires-Dist: mpi4py; extra == "full"
Requires-Dist: sphinx; extra == "full"
Requires-Dist: sphinx-autoapi; extra == "full"
Requires-Dist: sphinx_rtd_theme; extra == "full"
Requires-Dist: sphinx-book-theme; extra == "full"
